<?xml version='1.0' encoding='UTF-8'?>
<SHOP>
  <SHOPITEM>
    <VARIANTS>
      <VARIANT>
        <CODE>EP00461CR14</CODE>
        <STOCK>
          <WAREHOUSES>
            <WAREHOUSE>
              <NAME>Obchod Brno</NAME>
              <VALUE>0.0</VALUE>
            </WAREHOUSE>
            <WAREHOUSE>
              <NAME>Obchod Praha</NAME>
              <VALUE>0.0</VALUE>
            </WAREHOUSE>
          </WAREHOUSES>
        </STOCK>
        <PARAMETERS>
          <PARAMETER>
            <NAME>Velikost</NAME>
            <VALUE>30 EU</VALUE>
          </PARAMETER>
        </PARAMETERS>
      </VARIANT>
      <VARIANT>
        <CODE>EP00461CR16</CODE>
        <STOCK>
          <WAREHOUSES>
            <WAREHOUSE>
              <NAME>Obchod Brno</NAME>
              <VALUE>0.0</VALUE>
            </WAREHOUSE>
            <WAREHOUSE>
              <NAME>Obchod Praha</NAME>
              <VALUE>0.0</VALUE>
            </WAREHOUSE>
          </WAREHOUSES>
        </STOCK>
        <PARAMETERS>
          <PARAMETER>
            <NAME>Velikost</NAME>
            <VALUE>31 EU</VALUE>
          </PARAMETER>
        </PARAMETERS>
      </VARIANT>
    </VARIANTS>
  </SHOPITEM>
  <SHOPITEM>
    <VARIANTS>
      <VARIANT>
        <CODE>R1301BLILAC-M</CODE>
        <STOCK>
          <WAREHOUSES>
            <WAREHOUSE>
              <NAME>Obchod Brno</NAME>
              <VALUE>1.0</VALUE>
            </WAREHOUSE>
            <WAREHOUSE>
              <NAME>Obchod Praha</NAME>
              <VALUE>2.0</VALUE>
            </WAREHOUSE>
          </WAREHOUSES>
        </STOCK>
        <PARAMETERS>
          <PARAMETER>
            <NAME>Velikost</NAME>
            <VALUE>30 EU</VALUE>
          </PARAMETER>
        </PARAMETERS>
      </VARIANT>
    </VARIANTS>
  </SHOPITEM>
  <SHOPITEM>
    <VARIANTS>
      <VARIANT>
        <CODE>R1301BPINK-S</CODE>
        <STOCK>
          <WAREHOUSES>
            <WAREHOUSE>
              <NAME>Obchod Brno</NAME>
              <VALUE>0.0</VALUE>
            </WAREHOUSE>
            <WAREHOUSE>
              <NAME>Obchod Praha</NAME>
              <VALUE>0.0</VALUE>
            </WAREHOUSE>
          </WAREHOUSES>
        </STOCK>
        <PARAMETERS>
          <PARAMETER>
            <NAME>Velikost</NAME>
            <VALUE>30 EU</VALUE>
          </PARAMETER>
        </PARAMETERS>
      </VARIANT>
    </VARIANTS>
  </SHOPITEM>
  <SHOPITEM>
    <VARIANTS>
      <VARIANT>
        <CODE>EG01923TE06</CODE>
        <STOCK>
          <WAREHOUSES>
            <WAREHOUSE>
              <NAME>Obchod Brno</NAME>
              <VALUE>0.0</VALUE>
            </WAREHOUSE>
            <WAREHOUSE>
              <NAME>Obchod Praha</NAME>
              <VALUE>0.0</VALUE>
            </WAREHOUSE>
          </WAREHOUSES>
        </STOCK>
        <PARAMETERS>
          <PARAMETER>
            <NAME>Velikost</NAME>
            <VALUE>30 EU</VALUE>
          </PARAMETER>
        </PARAMETERS>
      </VARIANT>
    </VARIANTS>
  </SHOPITEM>
  <SHOPITEM>
    <VARIANTS>
      <VARIANT>
        <CODE>EG02155OD06</CODE>
        <STOCK>
          <WAREHOUSES>
            <WAREHOUSE>
              <NAME>Obchod Brno</NAME>
              <VALUE>-1.0</VALUE>
            </WAREHOUSE>
            <WAREHOUSE>
              <NAME>Obchod Praha</NAME>
              <VALUE>1.0</VALUE>
            </WAREHOUSE>
          </WAREHOUSES>
        </STOCK>
        <PARAMETERS>
          <PARAMETER>
            <NAME>Velikost</NAME>
            <VALUE>30 EU</VALUE>
          </PARAMETER>
        </PARAMETERS>
      </VARIANT>
    </VARIANTS>
  </SHOPITEM>
  <SHOPITEM>
    <VARIANTS>
      <VARIANT>
        <CODE>DR3337QZ-SAGEGR-10</CODE>
        <STOCK>
          <WAREHOUSES>
            <WAREHOUSE>
              <NAME>Obchod Brno</NAME>
              <VALUE>0.0</VALUE>
            </WAREHOUSE>
            <WAREHOUSE>
              <NAME>Obchod Praha</NAME>
              <VALUE>1.0</VALUE>
            </WAREHOUSE>
          </WAREHOUSES>
        </STOCK>
        <PARAMETERS>
          <PARAMETER>
            <NAME>Velikost</NAME>
            <VALUE>30 EU</VALUE>
          </PARAMETER>
        </PARAMETERS>
      </VARIANT>
    </VARIANTS>
  </SHOPITEM>
</SHOP>